try_or/__init__.py
try_or/py.typed
try_or-1.0.1.dist-info/METADATA
try_or-1.0.1.dist-info/WHEEL
try_or-1.0.1.dist-info/licenses/LICENSE
try_or-1.0.1.dist-info/RECORD
