Metadata-Version: 2.4
Name: try-or
Version: 1.0.1
Summary: A Python micro-library that returns try value or default.
Project-URL: Homepage, https://github.com/nakat-t/try-or-py
Project-URL: Repository, https://github.com/nakat-t/try-or-py
Project-URL: Issues, https://github.com/nakat-t/try-or-py/issues
Author-email: nakat-t <armaiti.wizard@gmail.com>
License-Expression: MIT
License-File: LICENSE
Keywords: default,except,or,try
Classifier: Development Status :: 4 - Beta
Classifier: License :: OSI Approved :: MIT License
Classifier: Operating System :: OS Independent
Classifier: Programming Language :: Python :: 3
Requires-Python: >=3.10
